odio/__init__.py
odio/common.py
odio/v1_1/__init__.py
odio/v1_2/__init__.py
odio/v1_2/elements.py
odio/v1_2/mapping.py
odio/v1_2/xml.py
odio/v1_3/__init__.py
odio/v1_3/elements.py
odio/v1_3/mapping.py
odio/v1_3/xml.py
odio-0.0.27.dist-info/METADATA
odio-0.0.27.dist-info/WHEEL
odio-0.0.27.dist-info/licenses/LICENSE
odio-0.0.27.dist-info/RECORD
